LICENSE
MANIFEST.in
README.rst
setup.cfg
setup.py
docs/changelog.rst
docs/index.rst
docs/installation.rst
docs/usage.rst
docs/assets/finite-automata.png
docs/assets/finite-automata.svg
py_romanify.egg-info/PKG-INFO
py_romanify.egg-info/SOURCES.txt
py_romanify.egg-info/dependency_links.txt
py_romanify.egg-info/top_level.txt
romanify/__init__.py